sthunder/__init__.py
sthunder/constants.py
sthunder/database/Database.py
sthunder/database/Untitled.ipynb
sthunder/database/__init__.py
sthunder/database/db_populate.py
sthunder/database/db_queries.py
sthunder/database/db_schema.py
sthunder/database/insert_land_classes.py
sthunder/lulc/__init__.py
sthunder/lulc/lulc.py
sthunder-0.1.0.dist-info/WHEEL
sthunder-0.1.0.dist-info/METADATA
sthunder-0.1.0.dist-info/RECORD
