Metadata-Version: 2.1
Name: sthunder
Version: 0.1.0
Summary: Self-Organizing Maps applied to thunderstorm analysis.
Author: Adriano P. Almeida
Author-email: adriano.almeida@inpe.br
Requires-Python: >=3.7,<4.0
Classifier: Programming Language :: Python :: 3
Classifier: Programming Language :: Python :: 3.7
Classifier: Programming Language :: Python :: 3.8
Classifier: Programming Language :: Python :: 3.9
